demo_gitlab_pkg/__init__.py
demo_gitlab_pkg-0.1.0.dist-info/WHEEL
demo_gitlab_pkg-0.1.0.dist-info/entry_points.txt
demo_gitlab_pkg-0.1.0.dist-info/METADATA
demo_gitlab_pkg-0.1.0.dist-info/RECORD
