Metadata-Version: 2.3
Name: demo-gitlab-pkg
Version: 0.1.0
Summary: Add your description here
Author: Mahamadou Salissou Aboubacar Alka
Author-email: Mahamadou Salissou Aboubacar Alka <alkasalissou@gmail.com>
Requires-Dist: pytest>=8.0.0,<9.0.0
Requires-Python: >=3.12
